{
  "scenario": "notifications-ui-no-backend",
  "findings": [
    {
      "requirementId": "R1",
      "status": "partial",
      "evidenceIncludes": ["component:NotificationBell", "code_hint:notification"],
      "missingLinksIncludes": ["notification_persistence"]
    },
    {
      "requirementId": "R2",
      "status": "partial",
      "evidenceIncludes": ["component:NotificationBell", "code_hint:notification"],
      "missingLinksIncludes": ["notification_persistence", "notification_api"]
    }
  ]
}
